typtrain/__init__.py
typtrain/__main__.py
typtrain/romaji2kana.py
typtrain/typtrain.py
typtrain/assets/dic.csv
typtrain-1.0.0.dist-info/LICENSE
typtrain-1.0.0.dist-info/METADATA
typtrain-1.0.0.dist-info/WHEEL
typtrain-1.0.0.dist-info/entry_points.txt
typtrain-1.0.0.dist-info/top_level.txt
typtrain-1.0.0.dist-info/RECORD
