Metadata-Version: 2.1
Name: typtrain
Version: 1.0.0
Summary: practice typing
Home-page: https://github.com/laddge/typtrain
Author: Laddge
Author-email: dev.laddge@gmail.com
License: MIT
Platform: UNKNOWN
